mortal_sftp/__init__.py
mortal_sftp/sftp_main.cpython-311-x86_64-linux-gnu.so
mortal_sftp-4.1.0.dist-info/METADATA
mortal_sftp-4.1.0.dist-info/WHEEL
mortal_sftp-4.1.0.dist-info/top_level.txt
mortal_sftp-4.1.0.dist-info/RECORD
